dimredtracer/__init__.py
dimredtracer/otel_setup.py
dimredtracer/tracer.py
dimredtracer-0.1.1.dist-info/METADATA
dimredtracer-0.1.1.dist-info/WHEEL
dimredtracer-0.1.1.dist-info/top_level.txt
dimredtracer-0.1.1.dist-info/RECORD
