Metadata-Version: 2.4
Name: dimredtracer
Version: 0.1.1
Summary: OpenTelemetry tracer for DimRed observability platform
Author-email: Jonathan Johannemann <jonathanjohannemann@gmail.com>
License: MIT
Project-URL: Homepage, https://github.com/DimRedLabs/dimred-python
Project-URL: Repository, https://github.com/DimRedLabs/dimred-python
Keywords: opentelemetry,observability,tracing,dimred
Classifier: Development Status :: 3 - Alpha
Classifier: Intended Audience :: Developers
Classifier: License :: OSI Approved :: MIT License
Classifier: Programming Language :: Python :: 3
Classifier: Programming Language :: Python :: 3.8
Classifier: Programming Language :: Python :: 3.9
Classifier: Programming Language :: Python :: 3.10
Classifier: Programming Language :: Python :: 3.11
Classifier: Programming Language :: Python :: 3.12
Requires-Python: >=3.8
Requires-Dist: opentelemetry-api>=1.22.0
Requires-Dist: opentelemetry-sdk>=1.22.0
Requires-Dist: opentelemetry-exporter-otlp-proto-http>=1.22.0
Provides-Extra: openai
Requires-Dist: openinference-instrumentation-openai>=0.1.0; extra == "openai"
Requires-Dist: openai>=1.0.0; extra == "openai"
